ratecounter/__init__.py
ratecounter/cli.py
ratecounter/main.py
ratecounter/tests/__init__.py
ratecounter/tests/test_cli.py
ratecounter/tests/test_data.py
ratecounter/tests/test_ratecounter.py
ratecounter/tests/test_score.py
RateCounter-1.1.dist-info/LICENSE
RateCounter-1.1.dist-info/METADATA
RateCounter-1.1.dist-info/WHEEL
RateCounter-1.1.dist-info/entry_points.txt
RateCounter-1.1.dist-info/top_level.txt
RateCounter-1.1.dist-info/zip-safe
RateCounter-1.1.dist-info/RECORD
