Metadata-Version: 2.1
Name: RateCounter
Version: 1.1
Summary: ratecounter - Nexus file rate counter for language phylogenies
Home-page: https://github.com/SimonGreenhill/RateCounter
Author: Simon J. Greenhill
Author-email: simon@simon.net.nz
License: BSD
Keywords: language-phylogenies
Platform: UNKNOWN
Classifier: Intended Audience :: Science/Research
Classifier: License :: OSI Approved :: BSD License
Classifier: Topic :: Scientific/Engineering
Classifier: Topic :: Scientific/Engineering :: Bio-Informatics
Classifier: Topic :: Software Development :: Libraries :: Python Modules
Classifier: Programming Language :: Python :: 3
Classifier: Programming Language :: Python :: 3.3
Classifier: Programming Language :: Python :: 3.4
Classifier: Programming Language :: Python :: 3.5
Classifier: Programming Language :: Python :: 3.6
Classifier: Programming Language :: Python :: 3.7
Requires-Dist: python-nexus (>=1.4)
